{"ele":9577,"carper":1,"md":"N","t":1,"f":"S","esae":"N","mnae":" ","dg":"12/08/2022","hg":"19:54:24","dv":"S","nadf":"rn-c0001-e009577-068-f","abr":[{"tpabr":"MU","cdabr":"16314","dt":"22/06/2022","ht":"14:37:51","tf":"S","and":"F","s":30,"st":30,"pst":"100,00","snt":0,"psnt":"0,00","si":30,"psi":"100,00","sni":0,"psni":"0,00","sa":30,"psa":"100,00","sna":0,"psna":"0,00","e":5378,"ea":5378,"pea":"100,00","ena":0,"pena":"0,00","esi":5378,"pesi":"100,00","esni":0,"pesni":"0,00","c":4581,"pc":"85,18","a":797,"pa":"14,82","tv":4581,"vvc":3389,"pvvc":"73,98","vscv":0,"vb":709,"pvb":"15,48","tvn":483,"ptvn":"10,54","vn":483,"pvn":"100,00","vnt":0,"pvnt":"0,00","vp":0,"pvp":"0,00","vv":2424,"pvv":"71,53","van":0,"pvan":"0,00","vansj":965,"pvansj":"28,47","vnom":2424,"pvnom":"100,00","cand":[{"seq":5,"n":19,"e":"N","vap":360,"pvap":"10,62","st":"Não eleito"},{"seq":6,"n":36,"e":"N","vap":164,"pvap":"4,84","st":"Não eleito"},{"seq":1,"n":31,"e":"S","vap":157,"pvap":"4,63","st":"2º turno"},{"seq":4,"n":51,"e":"N","vap":205,"pvap":"6,05","st":"Não eleito"},{"seq":9,"n":91,"e":"N","vap":441,"pvap":"13,01","st":"Não eleito"},{"seq":3,"n":12,"e":"N","vap":665,"pvap":"19,62","st":"Não eleito"},{"seq":8,"n":52,"e":"N","vap":413,"pvap":"12,19","st":"Não eleito"},{"seq":2,"n":14,"e":"S","vap":166,"pvap":"4,90","st":"2º turno"},{"seq":7,"n":24,"e":"N","vap":818,"pvap":"24,14","st":"Não eleito"}]},{"tpabr":"ZONA","cdabr":"62","dt":"22/06/2022","ht":"14:37:51","tf":"S","and":"F","s":30,"st":30,"pst":"100,00","snt":0,"psnt":"0,00","si":30,"psi":"100,00","sni":0,"psni":"0,00","sa":30,"psa":"100,00","sna":0,"psna":"0,00","e":5378,"ea":5378,"pea":"100,00","ena":0,"pena":"0,00","esi":5378,"pesi":"100,00","esni":0,"pesni":"0,00","c":4581,"pc":"85,18","a":797,"pa":"14,82","tv":4581,"vvc":3389,"pvvc":"73,98","vscv":0,"vb":709,"pvb":"15,48","tvn":483,"ptvn":"10,54","vn":483,"pvn":"100,00","vnt":0,"pvnt":"0,00","vp":0,"pvp":"0,00","vv":2424,"pvv":"71,53","van":0,"pvan":"0,00","vansj":965,"pvansj":"28,47","vnom":2424,"pvnom":"100,00","cand":[{"seq":3,"n":12,"e":"N","vap":665,"pvap":"19,62","st":"Não eleito"},{"seq":2,"n":14,"e":"S","vap":166,"pvap":"4,90","st":"2º turno"},{"seq":5,"n":19,"e":"N","vap":360,"pvap":"10,62","st":"Não eleito"},{"seq":7,"n":24,"e":"N","vap":818,"pvap":"24,14","st":"Não eleito"},{"seq":1,"n":31,"e":"S","vap":157,"pvap":"4,63","st":"2º turno"},{"seq":6,"n":36,"e":"N","vap":164,"pvap":"4,84","st":"Não eleito"},{"seq":4,"n":51,"e":"N","vap":205,"pvap":"6,05","st":"Não eleito"},{"seq":8,"n":52,"e":"N","vap":413,"pvap":"12,19","st":"Não eleito"},{"seq":9,"n":91,"e":"N","vap":441,"pvap":"13,01","st":"Não eleito"}]}]}