{"ele":9577,"carper":1,"md":"N","t":1,"f":"S","esae":"N","mnae":" ","dg":"12/08/2022","hg":"19:54:25","dv":"S","nadf":"rn-c0001-e009577-068-f","abr":[{"tpabr":"MU","cdabr":"18171","dt":"22/06/2022","ht":"14:37:53","tf":"S","and":"F","s":15,"st":15,"pst":"100,00","snt":0,"psnt":"0,00","si":15,"psi":"100,00","sni":0,"psni":"0,00","sa":15,"psa":"100,00","sna":0,"psna":"0,00","e":3777,"ea":3777,"pea":"100,00","ena":0,"pena":"0,00","esi":3777,"pesi":"100,00","esni":0,"pesni":"0,00","c":3218,"pc":"85,20","a":559,"pa":"14,80","tv":3218,"vvc":2765,"pvvc":"85,92","vscv":0,"vb":275,"pvb":"8,55","tvn":178,"ptvn":"5,53","vn":178,"pvn":"100,00","vnt":0,"pvnt":"0,00","vp":0,"pvp":"0,00","vv":1672,"pvv":"60,47","van":0,"pvan":"0,00","vansj":1093,"pvansj":"39,53","vnom":1672,"pvnom":"100,00","cand":[{"seq":7,"n":24,"e":"N","vap":457,"pvap":"16,53","st":"Não eleito"},{"seq":6,"n":36,"e":"N","vap":540,"pvap":"19,53","st":"Não eleito"},{"seq":2,"n":14,"e":"S","vap":144,"pvap":"5,21","st":"2º turno"},{"seq":3,"n":12,"e":"N","vap":161,"pvap":"5,82","st":"Não eleito"},{"seq":9,"n":91,"e":"N","vap":121,"pvap":"4,38","st":"Não eleito"},{"seq":5,"n":19,"e":"N","vap":432,"pvap":"15,62","st":"Não eleito"},{"seq":4,"n":51,"e":"N","vap":318,"pvap":"11,50","st":"Não eleito"},{"seq":1,"n":31,"e":"S","vap":207,"pvap":"7,49","st":"2º turno"},{"seq":8,"n":52,"e":"N","vap":385,"pvap":"13,92","st":"Não eleito"}]},{"tpabr":"ZONA","cdabr":"45","dt":"22/06/2022","ht":"14:37:53","tf":"S","and":"F","s":15,"st":15,"pst":"100,00","snt":0,"psnt":"0,00","si":15,"psi":"100,00","sni":0,"psni":"0,00","sa":15,"psa":"100,00","sna":0,"psna":"0,00","e":3777,"ea":3777,"pea":"100,00","ena":0,"pena":"0,00","esi":3777,"pesi":"100,00","esni":0,"pesni":"0,00","c":3218,"pc":"85,20","a":559,"pa":"14,80","tv":3218,"vvc":2765,"pvvc":"85,92","vscv":0,"vb":275,"pvb":"8,55","tvn":178,"ptvn":"5,53","vn":178,"pvn":"100,00","vnt":0,"pvnt":"0,00","vp":0,"pvp":"0,00","vv":1672,"pvv":"60,47","van":0,"pvan":"0,00","vansj":1093,"pvansj":"39,53","vnom":1672,"pvnom":"100,00","cand":[{"seq":3,"n":12,"e":"N","vap":161,"pvap":"5,82","st":"Não eleito"},{"seq":2,"n":14,"e":"S","vap":144,"pvap":"5,21","st":"2º turno"},{"seq":5,"n":19,"e":"N","vap":432,"pvap":"15,62","st":"Não eleito"},{"seq":7,"n":24,"e":"N","vap":457,"pvap":"16,53","st":"Não eleito"},{"seq":1,"n":31,"e":"S","vap":207,"pvap":"7,49","st":"2º turno"},{"seq":6,"n":36,"e":"N","vap":540,"pvap":"19,53","st":"Não eleito"},{"seq":4,"n":51,"e":"N","vap":318,"pvap":"11,50","st":"Não eleito"},{"seq":8,"n":52,"e":"N","vap":385,"pvap":"13,92","st":"Não eleito"},{"seq":9,"n":91,"e":"N","vap":121,"pvap":"4,38","st":"Não eleito"}]}]}