{"ele":9579,"carper":3,"md":"S","t":1,"f":"S","esae":"N","mnae":" ","dg":"12/08/2022","hg":"19:54:26","dv":"S","nadf":"rn-c0003-e009579-083-f","abr":[{"tpabr":"MU","cdabr":"16993","dt":"24/06/2022","ht":"16:09:50","tf":"S","and":"F","s":21,"st":21,"pst":"100,00","snt":0,"psnt":"0,00","si":21,"psi":"100,00","sni":0,"psni":"0,00","sa":21,"psa":"100,00","sna":0,"psna":"0,00","e":5178,"ea":5178,"pea":"100,00","ena":0,"pena":"0,00","esi":5178,"pesi":"100,00","esni":0,"pesni":"0,00","c":4411,"pc":"85,19","a":767,"pa":"14,81","tv":4411,"vvc":1263,"pvvc":"28,63","vscv":0,"vb":115,"pvb":"2,61","tvn":3033,"ptvn":"68,76","vn":94,"pvn":"3,10","vnt":2939,"pvnt":"96,90","vp":0,"pvp":"0,00","vv":847,"pvv":"67,06","van":300,"pvan":"23,75","vansj":116,"pvansj":"9,19","vnom":847,"pvnom":"100,00","cand":[{"seq":6,"n":15,"e":"N","vap":115,"pvap":"9,11","st":"Não eleito"},{"seq":7,"n":46,"e":"N","vap":301,"pvap":"23,83","st":"Não eleito"},{"seq":2,"n":11,"e":"S","vap":116,"pvap":"9,18","st":"2º turno"},{"seq":1,"n":13,"e":"S","vap":46,"pvap":"3,64","st":"2º turno"},{"seq":3,"n":22,"e":"N","vap":183,"pvap":"14,49","st":"Não eleito"},{"seq":4,"n":31,"e":"N","vap":117,"pvap":"9,26","st":"Não eleito"},{"seq":5,"n":12,"e":"N","vap":229,"pvap":"18,13","st":"Não eleito"},{"seq":8,"n":23,"e":"N","vap":108,"pvap":"8,55","st":"Não eleito"},{"seq":9,"n":91,"e":"N","vap":48,"pvap":"3,80","st":"Não eleito"}]},{"tpabr":"ZONA","cdabr":"62","dt":"24/06/2022","ht":"16:09:50","tf":"S","and":"F","s":21,"st":21,"pst":"100,00","snt":0,"psnt":"0,00","si":21,"psi":"100,00","sni":0,"psni":"0,00","sa":21,"psa":"100,00","sna":0,"psna":"0,00","e":5178,"ea":5178,"pea":"100,00","ena":0,"pena":"0,00","esi":5178,"pesi":"100,00","esni":0,"pesni":"0,00","c":4411,"pc":"85,19","a":767,"pa":"14,81","tv":4411,"vvc":1263,"pvvc":"28,63","vscv":0,"vb":115,"pvb":"2,61","tvn":3033,"ptvn":"68,76","vn":94,"pvn":"3,10","vnt":2939,"pvnt":"96,90","vp":0,"pvp":"0,00","vv":847,"pvv":"67,06","van":300,"pvan":"23,75","vansj":116,"pvansj":"9,19","vnom":847,"pvnom":"100,00","cand":[{"seq":2,"n":11,"e":"S","vap":116,"pvap":"9,18","st":"2º turno"},{"seq":5,"n":12,"e":"N","vap":229,"pvap":"18,13","st":"Não eleito"},{"seq":1,"n":13,"e":"S","vap":46,"pvap":"3,64","st":"2º turno"},{"seq":6,"n":15,"e":"N","vap":115,"pvap":"9,11","st":"Não eleito"},{"seq":3,"n":22,"e":"N","vap":183,"pvap":"14,49","st":"Não eleito"},{"seq":8,"n":23,"e":"N","vap":108,"pvap":"8,55","st":"Não eleito"},{"seq":4,"n":31,"e":"N","vap":117,"pvap":"9,26","st":"Não eleito"},{"seq":7,"n":46,"e":"N","vap":301,"pvap":"23,83","st":"Não eleito"},{"seq":9,"n":91,"e":"N","vap":48,"pvap":"3,80","st":"Não eleito"}]}]}