{"ele":9579,"carper":3,"md":"S","t":1,"f":"S","esae":"N","mnae":" ","dg":"12/08/2022","hg":"19:54:27","dv":"S","nadf":"rn-c0003-e009579-083-f","abr":[{"tpabr":"MU","cdabr":"17876","dt":"24/06/2022","ht":"16:09:50","tf":"S","and":"F","s":86,"st":86,"pst":"100,00","snt":0,"psnt":"0,00","si":86,"psi":"100,00","sni":0,"psni":"0,00","sa":86,"psa":"100,00","sna":0,"psna":"0,00","e":20823,"ea":20823,"pea":"100,00","ena":0,"pena":"0,00","esi":20823,"pesi":"100,00","esni":0,"pesni":"0,00","c":17732,"pc":"85,16","a":3091,"pa":"14,84","tv":17732,"vvc":4856,"pvvc":"27,39","vscv":0,"vb":569,"pvb":"3,20","tvn":12307,"ptvn":"69,41","vn":472,"pvn":"3,84","vnt":11835,"pvnt":"96,16","vp":0,"pvp":"0,00","vv":3034,"pvv":"62,48","van":1300,"pvan":"26,77","vansj":522,"pvansj":"10,75","vnom":3034,"pvnom":"100,00","cand":[{"seq":7,"n":46,"e":"N","vap":408,"pvap":"8,40","st":"Não eleito"},{"seq":3,"n":22,"e":"N","vap":742,"pvap":"15,28","st":"Não eleito"},{"seq":9,"n":91,"e":"N","vap":582,"pvap":"11,99","st":"Não eleito"},{"seq":8,"n":23,"e":"N","vap":572,"pvap":"11,78","st":"Não eleito"},{"seq":5,"n":12,"e":"N","vap":478,"pvap":"9,84","st":"Não eleito"},{"seq":6,"n":15,"e":"N","vap":497,"pvap":"10,23","st":"Não eleito"},{"seq":4,"n":31,"e":"N","vap":558,"pvap":"11,49","st":"Não eleito"},{"seq":2,"n":11,"e":"S","vap":522,"pvap":"10,75","st":"2º turno"},{"seq":1,"n":13,"e":"S","vap":497,"pvap":"10,23","st":"2º turno"}]},{"tpabr":"ZONA","cdabr":"40","dt":"24/06/2022","ht":"16:09:50","tf":"S","and":"F","s":86,"st":86,"pst":"100,00","snt":0,"psnt":"0,00","si":86,"psi":"100,00","sni":0,"psni":"0,00","sa":86,"psa":"100,00","sna":0,"psna":"0,00","e":20823,"ea":20823,"pea":"100,00","ena":0,"pena":"0,00","esi":20823,"pesi":"100,00","esni":0,"pesni":"0,00","c":17732,"pc":"85,16","a":3091,"pa":"14,84","tv":17732,"vvc":4856,"pvvc":"27,39","vscv":0,"vb":569,"pvb":"3,20","tvn":12307,"ptvn":"69,41","vn":472,"pvn":"3,84","vnt":11835,"pvnt":"96,16","vp":0,"pvp":"0,00","vv":3034,"pvv":"62,48","van":1300,"pvan":"26,77","vansj":522,"pvansj":"10,75","vnom":3034,"pvnom":"100,00","cand":[{"seq":2,"n":11,"e":"S","vap":522,"pvap":"10,75","st":"2º turno"},{"seq":5,"n":12,"e":"N","vap":478,"pvap":"9,84","st":"Não eleito"},{"seq":1,"n":13,"e":"S","vap":497,"pvap":"10,23","st":"2º turno"},{"seq":6,"n":15,"e":"N","vap":497,"pvap":"10,23","st":"Não eleito"},{"seq":3,"n":22,"e":"N","vap":742,"pvap":"15,28","st":"Não eleito"},{"seq":8,"n":23,"e":"N","vap":572,"pvap":"11,78","st":"Não eleito"},{"seq":4,"n":31,"e":"N","vap":558,"pvap":"11,49","st":"Não eleito"},{"seq":7,"n":46,"e":"N","vap":408,"pvap":"8,40","st":"Não eleito"},{"seq":9,"n":91,"e":"N","vap":582,"pvap":"11,99","st":"Não eleito"}]}]}