{"ele":9579,"carper":6,"t":1,"f":"S","esae":"N","mnae":" ","dg":"12/08/2022","hg":"19:54:42","dv":"S","nadf":"rn-c0006-e009579-079-f","abr":[{"tpabr":"MU","cdabr":"18554","agr":[{"n":200002519878,"tvtn":491,"tvtl":100,"tvan":491,"tval":100,"vag":0},{"n":200002519730,"tvtn":898,"tvtl":35,"tvan":898,"tval":35,"vag":0},{"n":200002519737,"tvtn":269,"tvtl":659,"tvan":269,"tval":659,"vag":0},{"n":200002520197,"tvtn":322,"tvtl":233,"tvan":371,"tval":233,"vag":0},{"n":200002519836,"tvtn":669,"tvtl":43,"tvan":669,"tval":43,"vag":0},{"n":200002519733,"tvtn":741,"tvtl":48,"tvan":741,"tval":48,"vag":0},{"n":200002519874,"tvtn":470,"tvtl":140,"tvan":470,"tval":140,"vag":0},{"n":200002520194,"tvtn":452,"tvtl":818,"tvan":523,"tval":818,"vag":0},{"n":200002519900,"tvtn":630,"tvtl":34,"tvan":630,"tval":34,"vag":0},{"n":200002519838,"tvtn":400,"tvtl":511,"tvan":400,"tval":511,"vag":0}],"parf":[{"n":14,"tvtn":77,"tvtl":241,"tvan":77,"tval":241},{"n":24,"tvtn":243,"tvtl":72,"tvan":243,"tval":72},{"n":44,"tvtn":77,"tvtl":370,"tvan":148,"tval":370},{"n":46,"tvtn":79,"tvtl":161,"tvan":128,"tval":161},{"n":66,"tvtn":298,"tvtl":207,"tvan":298,"tval":207}],"dt":"24/06/2022","ht":"16:10:11","tf":"S","and":"F","s":34,"st":34,"pst":"100,00","snt":0,"psnt":"0,00","si":34,"psi":"100,00","sni":0,"psni":"0,00","sa":34,"psa":"100,00","sna":0,"psna":"0,00","e":9999,"ea":9999,"pea":"100,00","ena":0,"pena":"0,00","esi":9999,"pesi":"100,00","esni":0,"pesni":"0,00","c":8517,"pc":"85,18","a":1482,"pa":"14,82","tv":8517,"vvc":8083,"pvvc":"94,90","vscv":0,"vb":246,"pvb":"2,89","tvn":188,"ptvn":"2,21","vn":188,"pvn":"100,00","vnt":0,"pvnt":"0,00","vp":0,"pvp":"0,00","vv":7963,"pvv":"98,52","vl":2621,"pvl":"32,91","van":0,"pvan":"0,00","vansj":120,"pvansj":"1,48","vnom":5342,"pvnom":"67,09","cand":[{"seq":30,"n":1101,"e":"N","vap":44,"pvap":"0,54","st":"Não eleito"},{"seq":23,"n":1106,"e":"N","vap":142,"pvap":"1,76","st":"Não eleito"},{"seq":54,"n":1306,"e":"N","vap":68,"pvap":"0,84","st":"Não eleito"},{"seq":39,"n":1303,"e":"N","vap":60,"pvap":"0,74","st":"Não eleito"},{"seq":31,"n":1301,"e":"N","vap":35,"pvap":"0,43","st":"Não eleito"},{"seq":42,"n":2203,"e":"N","vap":111,"pvap":"1,37","st":"Não eleito"},{"seq":13,"n":3104,"e":"N","vap":216,"pvap":"2,67","st":"Suplente"},{"seq":15,"n":6602,"e":"N","vap":227,"pvap":"2,81","st":"Suplente"},{"seq":33,"n":1206,"e":"N","vap":191,"pvap":"2,36","st":"Não eleito"},{"seq":27,"n":1205,"e":"N","vap":122,"pvap":"1,51","st":"Não eleito"},{"seq":56,"n":2202,"e":"N","vap":34,"pvap":"0,42","st":"Não eleito"},{"seq":10,"n":3103,"e":"N","vap":244,"pvap":"3,02","st":"Suplente"},{"seq":4,"n":3105,"e":"S","vap":46,"pvap":"0,57","st":"Eleito"},{"seq":17,"n":9101,"e":"N","vap":51,"pvap":"0,63","st":"Suplente"},{"seq":24,"n":1203,"e":"N","vap":288,"pvap":"3,56","st":"Não eleito"},{"seq":35,"n":1604,"e":"N","vap":272,"pvap":"3,37","st":"Não eleito"},{"seq":9,"n":9105,"e":"N","vap":141,"pvap":"1,74","st":"Suplente"},{"seq":20,"n":1104,"e":"N","vap":275,"pvap":"3,40","st":"Não eleito"},{"seq":41,"n":1103,"e":"N","vap":126,"pvap":"1,56","st":"Não eleito"},{"seq":29,"n":1305,"e":"N","vap":116,"pvap":"1,44","st":"Não eleito"},{"seq":45,"n":1605,"e":"N","vap":81,"pvap":"1,00","st":"Não eleito"},{"seq":34,"n":1601,"e":"N","vap":36,"pvap":"0,45","st":"Não eleito"},{"seq":46,"n":1602,"e":"N","vap":88,"pvap":"1,09","st":"Não eleito"},{"seq":28,"n":2302,"e":"N","vap":34,"pvap":"0,42","st":"Não eleito"},{"seq":7,"n":3106,"e":"S","vap":51,"pvap":"0,63","st":"Eleito"},{"seq":48,"n":4443,"e":"N","vap":71,"pvap":"0,88","st":"Não eleito"},{"seq":47,"n":4600,"e":"N","vap":49,"pvap":"0,61","st":"Não eleito"},{"seq":26,"n":4601,"e":"N","vap":79,"pvap":"0,98","st":"Não eleito"},{"seq":6,"n":9102,"e":"S","vap":110,"pvap":"1,36","st":"Eleito"},{"seq":16,"n":9104,"e":"N","vap":36,"pvap":"0,45","st":"Suplente"},{"seq":37,"n":1102,"e":"N","vap":45,"pvap":"0,56","st":"Não eleito"},{"seq":19,"n":1202,"e":"N","vap":78,"pvap":"0,96","st":"Não eleito"},{"seq":25,"n":1603,"e":"N","vap":209,"pvap":"2,59","st":"Não eleito"},{"seq":51,"n":2204,"e":"N","vap":206,"pvap":"2,55","st":"Não eleito"},{"seq":18,"n":2303,"e":"N","vap":36,"pvap":"0,45","st":"Não eleito"},{"seq":36,"n":2306,"e":"N","vap":34,"pvap":"0,42","st":"Não eleito"},{"seq":8,"n":2469,"e":"S","vap":130,"pvap":"1,61","st":"Eleito"},{"seq":50,"n":1204,"e":"N","vap":48,"pvap":"0,59","st":"Não eleito"},{"seq":43,"n":1304,"e":"N","vap":59,"pvap":"0,73","st":"Não eleito"},{"seq":57,"n":1606,"e":"N","vap":55,"pvap":"0,68","st":"Não eleito"},{"seq":38,"n":2201,"e":"N","vap":41,"pvap":"0,51","st":"Não eleito"},{"seq":32,"n":2304,"e":"N","vap":34,"pvap":"0,42","st":"Não eleito"},{"seq":49,"n":2305,"e":"N","vap":89,"pvap":"1,10","st":"Não eleito"},{"seq":2,"n":2414,"e":"S","vap":113,"pvap":"1,40","st":"Eleito"},{"seq":44,"n":1105,"e":"N","vap":37,"pvap":"0,46","st":"Não eleito"},{"seq":5,"n":1498,"e":"S","vap":36,"pvap":"0,45","st":"Eleito"},{"seq":14,"n":1487,"e":"N","vap":41,"pvap":"0,51","st":"Suplente"},{"seq":52,"n":2206,"e":"N","vap":58,"pvap":"0,72","st":"Não eleito"},{"seq":21,"n":2205,"e":"N","vap":41,"pvap":"0,51","st":"Não eleito"},{"seq":11,"n":3102,"e":"N","vap":39,"pvap":"0,48","st":"Suplente"},{"seq":3,"n":9103,"e":"S","vap":132,"pvap":"1,63","st":"Eleito"},{"seq":22,"n":1201,"e":"N","vap":171,"pvap":"2,12","st":"Não eleito"},{"seq":40,"n":1302,"e":"N","vap":62,"pvap":"0,77","st":"Não eleito"},{"seq":53,"n":2301,"e":"N","vap":42,"pvap":"0,52","st":"Não eleito"},{"seq":12,"n":3101,"e":"N","vap":34,"pvap":"0,42","st":"Suplente"},{"seq":55,"n":4400,"e":"N","vap":77,"pvap":"0,95","st":"Não eleito"},{"seq":1,"n":6600,"e":"S","vap":71,"pvap":"0,88","st":"Eleito"}]},{"tpabr":"ZONA","cdabr":"19","dt":"24/06/2022","ht":"16:10:11","tf":"S","and":"F","s":34,"st":34,"pst":"100,00","snt":0,"psnt":"0,00","si":34,"psi":"100,00","sni":0,"psni":"0,00","sa":34,"psa":"100,00","sna":0,"psna":"0,00","e":9999,"ea":9999,"pea":"100,00","ena":0,"pena":"0,00","esi":9999,"pesi":"100,00","esni":0,"pesni":"0,00","c":8517,"pc":"85,18","a":1482,"pa":"14,82","tv":8517,"vvc":8083,"pvvc":"94,90","vscv":0,"vb":246,"pvb":"2,89","tvn":188,"ptvn":"2,21","vn":188,"pvn":"100,00","vnt":0,"pvnt":"0,00","vp":0,"pvp":"0,00","vv":7963,"pvv":"98,52","vl":2621,"pvl":"32,91","van":0,"pvan":"0,00","vansj":120,"pvansj":"1,48","vnom":5342,"pvnom":"67,09","cand":[{"seq":29,"n":1305,"e":"N","vap":116,"pvap":"1,44","st":"Não eleito"},{"seq":54,"n":1306,"e":"N","vap":68,"pvap":"0,84","st":"Não eleito"},{"seq":39,"n":1303,"e":"N","vap":60,"pvap":"0,74","st":"Não eleito"},{"seq":31,"n":1301,"e":"N","vap":35,"pvap":"0,43","st":"Não eleito"},{"seq":40,"n":1302,"e":"N","vap":62,"pvap":"0,77","st":"Não eleito"},{"seq":5,"n":1498,"e":"S","vap":36,"pvap":"0,45","st":"Eleito"},{"seq":14,"n":1487,"e":"N","vap":41,"pvap":"0,51","st":"Suplente"},{"seq":35,"n":1604,"e":"N","vap":272,"pvap":"3,37","st":"Não eleito"},{"seq":57,"n":1606,"e":"N","vap":55,"pvap":"0,68","st":"Não eleito"},{"seq":45,"n":1605,"e":"N","vap":81,"pvap":"1,00","st":"Não eleito"},{"seq":34,"n":1601,"e":"N","vap":36,"pvap":"0,45","st":"Não eleito"},{"seq":46,"n":1602,"e":"N","vap":88,"pvap":"1,09","st":"Não eleito"},{"seq":25,"n":1603,"e":"N","vap":209,"pvap":"2,59","st":"Não eleito"},{"seq":52,"n":2206,"e":"N","vap":58,"pvap":"0,72","st":"Não eleito"},{"seq":51,"n":2204,"e":"N","vap":206,"pvap":"2,55","st":"Não eleito"},{"seq":42,"n":2203,"e":"N","vap":111,"pvap":"1,37","st":"Não eleito"},{"seq":56,"n":2202,"e":"N","vap":34,"pvap":"0,42","st":"Não eleito"},{"seq":38,"n":2201,"e":"N","vap":41,"pvap":"0,51","st":"Não eleito"},{"seq":21,"n":2205,"e":"N","vap":41,"pvap":"0,51","st":"Não eleito"},{"seq":53,"n":2301,"e":"N","vap":42,"pvap":"0,52","st":"Não eleito"},{"seq":28,"n":2302,"e":"N","vap":34,"pvap":"0,42","st":"Não eleito"},{"seq":18,"n":2303,"e":"N","vap":36,"pvap":"0,45","st":"Não eleito"},{"seq":32,"n":2304,"e":"N","vap":34,"pvap":"0,42","st":"Não eleito"},{"seq":49,"n":2305,"e":"N","vap":89,"pvap":"1,10","st":"Não eleito"},{"seq":36,"n":2306,"e":"N","vap":34,"pvap":"0,42","st":"Não eleito"},{"seq":2,"n":2414,"e":"S","vap":113,"pvap":"1,40","st":"Eleito"},{"seq":8,"n":2469,"e":"S","vap":130,"pvap":"1,61","st":"Eleito"},{"seq":13,"n":3104,"e":"N","vap":216,"pvap":"2,67","st":"Suplente"},{"seq":7,"n":3106,"e":"S","vap":51,"pvap":"0,63","st":"Eleito"},{"seq":10,"n":3103,"e":"N","vap":244,"pvap":"3,02","st":"Suplente"},{"seq":11,"n":3102,"e":"N","vap":39,"pvap":"0,48","st":"Suplente"},{"seq":12,"n":3101,"e":"N","vap":34,"pvap":"0,42","st":"Suplente"},{"seq":4,"n":3105,"e":"S","vap":46,"pvap":"0,57","st":"Eleito"},{"seq":48,"n":4443,"e":"N","vap":71,"pvap":"0,88","st":"Não eleito"},{"seq":55,"n":4400,"e":"N","vap":77,"pvap":"0,95","st":"Não eleito"},{"seq":47,"n":4600,"e":"N","vap":49,"pvap":"0,61","st":"Não eleito"},{"seq":26,"n":4601,"e":"N","vap":79,"pvap":"0,98","st":"Não eleito"},{"seq":15,"n":6602,"e":"N","vap":227,"pvap":"2,81","st":"Suplente"},{"seq":1,"n":6600,"e":"S","vap":71,"pvap":"0,88","st":"Eleito"},{"seq":17,"n":9101,"e":"N","vap":51,"pvap":"0,63","st":"Suplente"},{"seq":6,"n":9102,"e":"S","vap":110,"pvap":"1,36","st":"Eleito"},{"seq":16,"n":9104,"e":"N","vap":36,"pvap":"0,45","st":"Suplente"},{"seq":3,"n":9103,"e":"S","vap":132,"pvap":"1,63","st":"Eleito"},{"seq":9,"n":9105,"e":"N","vap":141,"pvap":"1,74","st":"Suplente"},{"seq":37,"n":1102,"e":"N","vap":45,"pvap":"0,56","st":"Não eleito"},{"seq":30,"n":1101,"e":"N","vap":44,"pvap":"0,54","st":"Não eleito"},{"seq":23,"n":1106,"e":"N","vap":142,"pvap":"1,76","st":"Não eleito"},{"seq":44,"n":1105,"e":"N","vap":37,"pvap":"0,46","st":"Não eleito"},{"seq":20,"n":1104,"e":"N","vap":275,"pvap":"3,40","st":"Não eleito"},{"seq":41,"n":1103,"e":"N","vap":126,"pvap":"1,56","st":"Não eleito"},{"seq":19,"n":1202,"e":"N","vap":78,"pvap":"0,96","st":"Não eleito"},{"seq":33,"n":1206,"e":"N","vap":191,"pvap":"2,36","st":"Não eleito"},{"seq":27,"n":1205,"e":"N","vap":122,"pvap":"1,51","st":"Não eleito"},{"seq":50,"n":1204,"e":"N","vap":48,"pvap":"0,59","st":"Não eleito"},{"seq":22,"n":1201,"e":"N","vap":171,"pvap":"2,12","st":"Não eleito"},{"seq":24,"n":1203,"e":"N","vap":288,"pvap":"3,56","st":"Não eleito"},{"seq":43,"n":1304,"e":"N","vap":59,"pvap":"0,73","st":"Não eleito"}]}]}